uml_generator/__init__.py
uml_generator/__main__.py
uml_generator/cli.py
uml_generator/config.py
uml_generator/llm_provider.py
uml_generator/uml_render.py
python_uml_generator-0.1.1.dist-info/METADATA
python_uml_generator-0.1.1.dist-info/WHEEL
python_uml_generator-0.1.1.dist-info/entry_points.txt
python_uml_generator-0.1.1.dist-info/top_level.txt
python_uml_generator-0.1.1.dist-info/RECORD
