Metadata-Version: 2.4
Name: python-uml-generator
Version: 0.1.1
Summary: A LangChain-based AI agent that converts natural language to UML diagrams (PlantUML)
Author-email: Milind Nair <nairmilind3@gmail.com>
License-Expression: MIT
Project-URL: Homepage, https://github.com/milind-nair/uml-generator
Classifier: Programming Language :: Python :: 3
Classifier: Operating System :: OS Independent
Requires-Python: >=3.8
Requires-Dist: requests
Requires-Dist: python-dotenv
Requires-Dist: plantuml
Requires-Dist: langchain
Requires-Dist: langchain-openai
Requires-Dist: langchain-google-genai
Requires-Dist: six
